config_handler/__init__.py
config_handler/__main__.py
config_handler/_ui.py
config_handler/exceptions.py
config_handler/info.py
config_handler/_interactive/__init__.py
config_handler/_interactive/create_new_config.py
config_handler/_interactive/open_config.py
config_handler/_interactive/utils.py
config_handler/advanced/__init__.py
config_handler/advanced/compression/__init__.py
config_handler/advanced/compression/lz4.py
config_handler/advanced/compression/zlib.py
config_handler/advanced/encryption/__init__.py
config_handler/advanced/encryption/aes256.py
config_handler/simple/__init__.py
ConfigHandler_python-2.0.2.dist-info/LICENSE.md
ConfigHandler_python-2.0.2.dist-info/METADATA
ConfigHandler_python-2.0.2.dist-info/WHEEL
ConfigHandler_python-2.0.2.dist-info/entry_points.txt
ConfigHandler_python-2.0.2.dist-info/top_level.txt
ConfigHandler_python-2.0.2.dist-info/RECORD
