Metadata-Version: 2.1
Name: ConfigHandler-python
Version: 2.0.2
Summary: Create, update, and remove values from a configuration file made by ConfigHandler.
Author-email: Chris1320 <chris1320is@protonmail.com>
License: MIT
Project-URL: Repository, https://github.com/Chris1320/ConfigHandler-python
Classifier: Development Status :: 4 - Beta
Classifier: License :: OSI Approved :: MIT License
Classifier: Programming Language :: Python :: 3.10
Classifier: Programming Language :: Python :: 3.11
Requires-Python: >=3.10
License-File: LICENSE.md
Provides-Extra: full
Requires-Dist: pycryptodomex (==3.15.0) ; extra == 'full'
Requires-Dist: prettytable (==3.5.0) ; extra == 'full'
Requires-Dist: lz4 (==4.0.2) ; extra == 'full'
Provides-Extra: test
Requires-Dist: pytest (==7.2.0) ; extra == 'test'
Requires-Dist: pytest-cov (==4.0.0) ; extra == 'test'
Requires-Dist: pytest-benchmark (==4.0.0) ; extra == 'test'
